README.md
setup.py
smsactivaterukdts/__init__.py
smsactivaterukdts/actions.py
smsactivaterukdts/activations.py
smsactivaterukdts/datatype.py
smsactivaterukdts/errors.py
smsactivaterukdts/helper.py
smsactivaterukdts/models.py
smsactivaterukdts/services.py
smsactivaterukdts/sms.py
smsactivaterukdts.egg-info/PKG-INFO
smsactivaterukdts.egg-info/SOURCES.txt
smsactivaterukdts.egg-info/dependency_links.txt
smsactivaterukdts.egg-info/requires.txt
smsactivaterukdts.egg-info/top_level.txt