Metadata-Version: 2.1
Name: smsactivaterukdts
Version: 1.0.0
Summary: Wrapper for automatic reception of SMS-messages by sms-activate.ru
Home-page: https://github.com/kubradts/smsactive
Author: tezmen
Author-email: kubraadts@gmail.com
License: Apache License, Version 2.0, see LICENSE file
Download-URL: https://github.com/tezmen/python-sms-activate-ru/archive/master.zip
Keywords: sms,revice,sms-activate-ru,autoreg
Platform: UNKNOWN
Classifier: License :: OSI Approved :: Apache Software License
Classifier: Operating System :: OS Independent
Classifier: Environment :: Console
Classifier: Development Status :: 3 - Alpha
Classifier: Programming Language :: Python
Classifier: Programming Language :: Python :: 3.5
Classifier: Programming Language :: Python :: 3.6
Classifier: Programming Language :: Python :: 3.7
Classifier: Programming Language :: Python :: Implementation :: PyPy
